{
  "grammars": [
    {
      "name": "mlir",
      "camelcase": "Mlir",
      "scope": "source.mlir",
      "path": ".",
      "file-types": [
        "mlir"
      ],
      "highlights": "queries/highlights.scm",
      "locals": "queries/locals.scm",
      "injections": "queries/injections.scm"
    }
  ],
  "metadata": {
    "version": "0.1.0",
    "license": "Apache-2.0",
    "description": "Tree sitter grammar for MLIR",
    "authors": [
      {
        "name": "Buyun Xu",
        "email": "xubuyun@outlook.com"
      },
      {
        "name": "Ramkumar Ramachandra"
      }
    ],
    "links": {
      "repository": "https://github.com/felixtensor/tree-sitter-mlir"
    }
  },
  "bindings": {
    "c": true,
    "go": true,
    "node": true,
    "python": true,
    "rust": true,
    "swift": true
  }
}
